mcp_graphql/__init__.py
mcp_graphql/__main__.py
mcp_graphql/py.typed
mcp_graphql/server.py
mcp_graphql/types.py
mcp_graphql-0.4.0.dist-info/METADATA
mcp_graphql-0.4.0.dist-info/WHEEL
mcp_graphql-0.4.0.dist-info/entry_points.txt
mcp_graphql-0.4.0.dist-info/RECORD
