Metadata-Version: 2.4
Name: mcp-graphql
Version: 0.4.0
Summary: MCP server for GraphQL
Requires-Python: >=3.11
Requires-Dist: aiohttp>=3.11.16
Requires-Dist: click>=8.1.8
Requires-Dist: gql>=3.5.2
Requires-Dist: mcp[cli]>=1.10.1
